Metadata-Version: 2.1
Name: epilearn
Version: 0.0.1
Summary: A Pytorch library for machine learning in epidemic modeling
Home-page: https://github.com/Emory-Melody/EpiLearn
Author: Emory-Melody
Author-email: zevin.liu@gmail.com
Maintainer: MSU-DSE
License: MIT
Classifier: Intended Audience :: Developers
Classifier: Intended Audience :: Education
Classifier: Intended Audience :: Science/Research
Classifier: Programming Language :: Python :: 3
Classifier: License :: OSI Approved :: Apache Software License
Classifier: Topic :: Scientific/Engineering :: Mathematics
Classifier: Topic :: Software Development :: Libraries :: Python Modules
Classifier: Topic :: Software Development :: Libraries
License-File: LICENSE
Requires-Dist: matplotlib >=3.9.0
Requires-Dist: numpy ==1.26.4
Requires-Dist: torch >=1.2.0
Requires-Dist: scipy >=1.3.1
Requires-Dist: networkx ==3.2.1
Requires-Dist: Pillow >=7.0.0
Requires-Dist: scikit-learn >=0.22.1
Requires-Dist: tqdm >=3.0
Requires-Dist: seaborn >=0.13.2
Requires-Dist: xgboost >=2.0.3
Requires-Dist: statsmodels >=0.14.2
Requires-Dist: streamlit ==1.34.0
Requires-Dist: pyvis ==0.3.2
Requires-Dist: plotly ==5.22.0
Requires-Dist: fastdtw ==0.3.4
Requires-Dist: einops ==0.8.0
